Workbook
Name Slicer_Category1: #N/A
Name Slicer_Region: #N/A
Name Slicer_Sales_Person: #N/A
Name Slicer_Segment: #N/A
Name Slicer_Year: #N/A

Sheet SalesData
A1: Order ID | B1: Order Date | C1: Customer Name | D1: Region | E1: State | F1: Category | G1: Sub Category | H1: Product Name | I1: Sales | J1: Quantity | K1: Discount | L1: Profit | M1: Sales Person | N1: Segment | O1: salesman rank | P1: Unit price | Q1: Order_Date_New | R1: Year | S1: Month_num | T1: Month_name | U1: profit_margin | V1: Discount_Bucket
A2: ORD100002 | B2: 45688 | C2: Customer 87 | D2: South | E2: Karnataka | F2: Office Supplies | G2: Binders | H2: Document Case | I2: 5565.9 | J2: 10 | K2: 0 | L2: 421.59 | M2: Amit | N2: Home Office | O2: =IF(AND(I2>5000,J2>7),"Good","Bad") -> Good | P2: =I2/J2 -> 556.59 | Q2: 45688 | R2: =YEAR(Table1[[#This Row],[Order_Date_New]]) -> 2025 | S2: =MONTH(Table1[[#This Row],[Order_Date_New]]) -> 1 | T2: =TEXT(Table1[[#This Row],[Order_Date_New]],"mmmm") -> January | U2: =Table1[[#This Row],[Profit]]/Table1[[#This Row],[Sales]] -> 0.075745163 | V2: =IF(Table1[[#This Row],[Discount]]=0,"No Discount",IF(Table1[[#This Row],[Discount]]<=0.1,"Low",IF(Table1[[#This Row],[Discount]]<=0.2,"medium","high"))) -> No Discount
A3: ORD100003 | B3: 45696 | C3: Customer 64 | D3: West | E3: Gujarat | F3: Office Supplies | G3: Writing | H3: Highlighter | I3: 997.04 | J3: 4 | K3: 0.25 | L3: -161.72 | M3: Vikram | N3: Consumer | O3: =IF(AND(I3>5000,J3>7),"Good","Bad") -> Bad | P3: =I3/J3 -> 249.26 | Q3: 45696 | R3: =YEAR(Table1[[#This Row],[Order_Date_New]]) -> 2025 | S3: =MONTH(Table1[[#This Row],[Order_Date_New]]) -> 2 | T3: =TEXT(Table1[[#This Row],[Order_Date_New]],"mmmm") -> February | U3: =Table1[[#This Row],[Profit]]/Table1[[#This Row],[Sales]] -> -0.16220011 | V3: =IF(Table1[[#This Row],[Discount]]=0,"No Discount",IF(Table1[[#This Row],[Discount]]<=0.1,"Low",IF(Table1[[#This Row],[Discount]]<=0.2,"medium","high"))) -> high
A4: ORD100004 | B4: 45961 | C4: Customer 49 | D4: West | E4: Gujarat | F4: Office Supplies | G4: Paper | H4: Notebook | I4: 1711.71 | J4: 7 | K4: 0 | L4: 356.91 | M4: Priya | N4: Small Business | O4: =IF(AND(I4>5000,J4>7),"Good","Bad") -> Bad | P4: =I4/J4 -> 244.53 | Q4: 45961 | R4: =YEAR(Table1[[#This Row],[Order_Date_New]]) -> 2025 | S4: =MONTH(Table1[[#This Row],[Order_Date_New]]) -> 10 | T4: =TEXT(Table1[[#This Row],[Order_Date_New]],"mmmm") -> October | U4: =Table1[[#This Row],[Profit]]/Table1[[#This Row],[Sales]] -> 0.20851079 | V4: =IF(Table1[[#This Row],[Discount]]=0,"No Discount",IF(Table1[[#This Row],[Discount]]<=0.1,"Low",IF(Table1[[#This Row],[Discount]]<=0.2,"medium","high"))) -> No Discount
A5: ORD100005 | B5: 45742 | C5: Customer 75 | D5: West | E5: Rajasthan | F5: Office Supplies | G5: Paper | H5: Notebook | I5: 1435.1 | J5: 5 | K5: 0.3 | L5: -122.01 | M5: Pooja | N5: Consumer | O5: =IF(AND(I5>5000,J5>7),"Good","Bad") -> Bad | P5: =I5/J5 -> 287.02 | Q5: 45742 | R5: =YEAR(Table1[[#This Row],[Order_Date_New]]) -> 2025 | S5: =MONTH(Table1[[#This Row],[Order_Date_New]]) -> 3 | T5: =TEXT(Table1[[#This Row],[Order_Date_New]],"mmmm") -> March | U5: =Table1[[#This Row],[Profit]]/Table1[[#This Row],[Sales]] -> -0.085018466 | V5: =IF(Table1[[#This Row],[Discount]]=0,"No Discount",IF(Table1[[#This Row],[Discount]]<=0.1,"Low",IF(Table1[[#This Row],[Discount]]<=0.2,"medium","high"))) -> high
A6: ORD100006 | B6: 45698 | C6: Customer 191 | D6: North | E6: Punjab | F6: Office Supplies | G6: Writing | H6: Pen Pack | I6: 1413.08 | J6: 2 | K6: 0.1 | L6: 416.9 | M6: Vikram | N6: Home Office | O6: =IF(AND(I6>5000,J6>7),"Good","Bad") -> Bad | P6: =I6/J6 -> 706.54 | Q6: 45698 | R6: =YEAR(Table1[[#This Row],[Order_Date_New]]) -> 2025 | S6: =MONTH(Table1[[#This Row],[Order_Date_New]]) -> 2 | T6: =TEXT(Table1[[#This Row],[Order_Date_New]],"mmmm") -> February | U6: =Table1[[#This Row],[Profit]]/Table1[[#This Row],[Sales]] -> 0.2950293 | V6: =IF(Table1[[#This Row],[Discount]]=0,"No Discount",IF(Table1[[#This Row],[Discount]]<=0.1,"Low",IF(Table1[[#This Row],[Discount]]<=0.2,"medium","high"))) -> Low
A7: ORD100007 | B7: 45629 | C7: Customer 166 | D7: South | E7: Tamil Nadu | F7: Furniture | G7: Chairs | H7: Gaming Chair | I7: 6869.16 | J7: 9 | K7: 0 | L7: 721.16 | M7: Pooja | N7: Home Office | O7: =IF(AND(I7>5000,J7>7),"Good","Bad") -> Good | P7: =I7/J7 -> 763.24 | Q7: 45629 | R7: =YEAR(Table1[[#This Row],[Order_Date_New]]) -> 2024 | S7: =MONTH(Table1[[#This Row],[Order_Date_New]]) -> 12 | T7: =TEXT(Table1[[#This Row],[Order_Date_New]],"mmmm") -> December | U7: =Table1[[#This Row],[Profit]]/Table1[[#This Row],[Sales]] -> 0.10498518 | V7: =IF(Table1[[#This Row],[Discount]]=0,"No Discount",IF(Table1[[#This Row],[Discount]]<=0.1,"Low",IF(Table1[[#This Row],[Discount]]<=0.2,"medium","high"))) -> No Discount
A8: ORD100008 | B8: 45580 | C8: Customer 167 | D8: West | E8: Maharashtra | F8: Furniture | G8: Chairs | H8: Visitor Chair | I8: 5509.7 | J8: 10 | K8: 0.2 | L8: -457.71 | M8: Karan | N8: Home Office | O8: =IF(AND(I8>5000,J8>7),"Good","Bad") -> Good | P8: =I8/J8 -> 550.97 | Q8: 45580 | R8: =YEAR(Table1[[#This Row],[Order_Date_New]]) -> 2024 | S8: =MONTH(Table1[[#This Row],[Order_Date_New]]) -> 10 | T8: =TEXT(Table1[[#This Row],[Order_Date_New]],"mmmm") -> October | U8: =Table1[[#This Row],[Profit]]/Table1[[#This Row],[Sales]] -> -0.083073489 | V8: =IF(Table1[[#This Row],[Discount]]=0,"No Discount",IF(Table1[[#This Row],[Discount]]<=0.1,"Low",IF(Table1[[#This Row],[Discount]]<=0.2,"medium","high"))) -> medium
A9: ORD100009 | B9: 45903 | C9: Customer 94 | D9: West | E9: Gujarat | F9: Technology | G9: Computers | H9: Laptop | I9: 4643.04 | J9: 6 | K9: 0.25 | L9: -634.04 | M9: Karan | N9: Consumer | O9: =IF(AND(I9>5000,J9>7),"Good","Bad") -> Bad | P9: =I9/J9 -> 773.84 | Q9: 45903 | R9: =YEAR(Table1[[#This Row],[Order_Date_New]]) -> 2025 | S9: =MONTH(Table1[[#This Row],[Order_Date_New]]) -> 9 | T9: =TEXT(Table1[[#This Row],[Order_Date_New]],"mmmm") -> September | U9: =Table1[[#This Row],[Profit]]/Table1[[#This Row],[Sales]] -> -0.13655708 | V9: =IF(Table1[[#This Row],[Discount]]=0,"No Discount",IF(Table1[[#This Row],[Discount]]<=0.1,"Low",IF(Table1[[#This Row],[Discount]]<=0.2,"medium","high"))) -> high
A10: ORD100010 | B10: 45567 | C10: Customer 39 | D10: North | E10: Uttarakhand | F10: Furniture | G10: Storage | H10: Cabinet | I10: 101.16 | J10: 6 | K10: 0.3 | L10: -23.27 | M10: Vikram | N10: Corporate | O10: =IF(AND(I10>5000,J10>7),"Good","Bad") -> Bad | P10: =I10/J10 -> 16.86 | Q10: 45567 | R10: =YEAR(Table1[[#This Row],[Order_Date_New]]) -> 2024 | S10: =MONTH(Table1[[#This Row],[Order_Date_New]]) -> 10 | T10: =TEXT(Table1[[#This Row],[Order_Date_New]],"mmmm") -> October | U10: =Table1[[#This Row],[Profit]]/Table1[[#This Row],[Sales]] -> -0.23003163 | V10: =IF(Table1[[#This Row],[Discount]]=0,"No Discount",IF(Table1[[#This Row],[Discount]]<=0.1,"Low",IF(Table1[[#This Row],[Discount]]<=0.2,"medium","high"))) -> high
A11: ORD100011 | B11: 45484 | C11: Customer 196 | D11: South | E11: Telangana | F11: Technology | G11: Computers | H11: Laptop | I11: 2687.4 | J11: 10 | K11: 0.15 | L11: 145.56 | M11: Priya | N11: Consumer | O11: =IF(AND(I11>5000,J11>7),"Good","Bad") -> Bad | P11: =I11/J11 -> 268.74 | Q11: 45484 | R11: =YEAR(Table1[[#This Row],[Order_Date_New]]) -> 2024 | S11: =MONTH(Table1[[#This Row],[Order_Date_New]]) -> 7 | T11: =TEXT(Table1[[#This Row],[Order_Date_New]],"mmmm") -> July | U11: =Table1[[#This Row],[Profit]]/Table1[[#This Row],[Sales]] -> 0.054163876 | V11: =IF(Table1[[#This Row],[Discount]]=0,"No Discount",IF(Table1[[#This Row],[Discount]]<=0.1,"Low",IF(Table1[[#This Row],[Discount]]<=0.2,"medium","high"))) -> medium
A12: ORD100012 | B12: 45368 | C12: Customer 26 | D12: North | E12: Haryana | F12: Technology | G12: Phones | H12: Smartphone | I12: 1715.22 | J12: 3 | K12: 0.15 | L12: 175.1 | M12: Rahul | N12: Corporate | O12: =IF(AND(I12>5000,J12>7),"Good","Bad") -> Bad | P12: =I12/J12 -> 571.74 | Q12: 45368 | R12: =YEAR(Table1[[#This Row],[Order_Date_New]]) -> 2024 | S12: =MONTH(Table1[[#This Row],[Order_Date_New]]) -> 3 | T12: =TEXT(Table1[[#This Row],[Order_Date_New]],"mmmm") -> March | U12: =Table1[[#This Row],[Profit]]/Table1[[#This Row],[Sales]] -> 0.10208603 | V12: =IF(Table1[[#This Row],[Discount]]=0,"No Discount",IF(Table1[[#This Row],[Discount]]<=0.1,"Low",IF(Table1[[#This Row],[Discount]]<=0.2,"medium","high"))) -> medium
A13: ORD100013 | B13: 45428 | C13: Customer 100 | D13: West | E13: Gujarat | F13: Office Supplies | G13: Paper | H13: Notebook | I13: 572.04 | J13: 1 | K13: 0.15 | L13: 117.9 | M13: Pooja | N13: Home Office | O13: =IF(AND(I13>5000,J13>7),"Good","Bad") -> Bad | P13: =I13/J13 -> 572.04 | Q13: 45428 | R13: =YEAR(Table1[[#This Row],[Order_Date_New]]) -> 2024 | S13: =MONTH(Table1[[#This Row],[Order_Date_New]]) -> 5 | T13: =TEXT(Table1[[#This Row],[Order_Date_New]],"mmmm") -> May | U13: =Table1[[#This Row],[Profit]]/Table1[[#This Row],[Sales]] -> 0.20610447 | V13: =IF(Table1[[#This Row],[Discount]]=0,"No Discount",IF(Table1[[#This Row],[Discount]]<=0.1,"Low",IF(Table1[[#This Row],[Discount]]<=0.2,"medium","high"))) -> medium
... A1001: ORD101001 | B1001: 45611 | C1001: Customer 144 | D1001: West | E1001: Rajasthan | F1001: Furniture | G1001: Tables | H1001: Conference Table | I1001: 5809.85 | J1001: 5 | K1001: 0.15 | L1001: 1528.75 | M1001: Karan | N1001: Home Office | O1001: =IF(AND(I1001>5000,J1001>7),"Good","Bad") -> Bad | P1001: =I1001/J1001 -> 1161.97 | Q1001: 45611 | R1001: =YEAR(Table1[[#This Row],[Order_Date_New]]) -> 2024 | S1001: =MONTH(Table1[[#This Row],[Order_Date_New]]) -> 11 | T1001: =TEXT(Table1[[#This Row],[Order_Date_New]],"mmmm") -> November | U1001: =Table1[[#This Row],[Profit]]/Table1[[#This Row],[Sales]] -> 0.26313072 | V1001: =IF(Table1[[#This Row],[Discount]]=0,"No Discount",IF(Table1[[#This Row],[Discount]]<=0.1,"Low",IF(Table1[[#This Row],[Discount]]<=0.2,"medium","high"))) -> medium

Sheet KPI
A3: total sales | B3: Sum of Sales
B4: 3465455.1 | E4: KPI
E5: Total sales | F5: =GETPIVOTDATA("Sales",KPI!$B$3) -> 3465455.1
A6: total profit | B6: Sum of Profit | E6: Total profit | F6: =GETPIVOTDATA("Profit",KPI!$B$6) -> 359412.61
B7: 359412.61 | E7: Total orders | F7: =GETPIVOTDATA("Order ID",KPI!$B$13) -> 1000
E8: Total quantity sold | F8: =GETPIVOTDATA("Quantity",KPI!$B$16) -> 5541
E9: avg order vaue | F9: =GETPIVOTDATA("Sales",KPI!$B$10) -> 3465.4551
A10: average sales | B10: Average of Sales | E10: Profit margin | F10: =GETPIVOTDATA("profit_margin",KPI!$B$19) -> 0.10481829
B11: 3465.4551
A13: count of product | B13: Count of Order ID
B14: 1000
A16: total quantity | B16: Sum of Quantity
B17: 5541
A19: profit margin | B19: Average of profit_margin
B20: 0.10481829

Sheet Time series Analysis
A2: 1. Which month generate highest sales?
A4: Row Labels | B4: Sum of Sales
A5: January | B5: 355999.33
A6: February | B6: 140042.73
A7: March | B7: 367070.95
A8: April | B8: 310082.86
A9: May | B9: 266511
A10: June | B10: 287893.18
A11: July | B11: 346784.48
A12: August | B12: 239372.65
A13: September | B13: 297494.26
A14: October | B14: 225012.93
A15: November | B15: 284343.11
A16: December | B16: 344847.58
A17: Grand Total | B17: 3465455.1

Sheet Regional Analysis
A1: Highest revenue region
A2: Row Labels | B2: Sum of Sales
A3: West | B3: 892650.61
A4: North | B4: 889350.76
A5: East | B5: 888709.54
A6: South | B6: 794744.15
A7: Grand Total | B7: 3465455.1

Sheet Product  Analysis
A1: Top 10 Products
A3: Row Labels | B3: Sum of Sales
A4: Conference Table | B4: 213389.86
A5: Mini PC | B5: 172205.52
A6: Headset | B6: 165051.1
A7: Keyboard | B7: 158867.86
A8: File Folder | B8: 155448.88
A9: Gaming Chair | B9: 138350.93
A10: A4 Paper | B10: 137670.47
A11: Smartphone | B11: 135858.04
A12: Document Case | B12: 133570.01
A13: Office Chair | B13: 132379.78
A14: Grand Total | B14: 1542792.4

Sheet Salesman Performance
B2: Best salesperson
B3: Row Labels | C3: Sum of Sales
B4: Pooja | C4: 405495.69
B5: Rohit | C5: 395387.21
B6: Rahul | C6: 374029.37
B7: Priya | C7: 351157.02
B8: Amit | C8: 350695.38
B9: Anjali | C9: 341609.58
B10: Vikram | C10: 334323.11
B11: Sneha | C11: 321778.47
B12: Karan | C12: 311338.44
B13: Neha | C13: 279640.79
B14: Grand Total | C14: 3465455.1

Sheet Category Analysis
C2: Highest selling category
C3: Row Labels | D3: Sum of Sales
C4: Office Supplies | D4: 1166785.5
C5: Technology | D5: 1157702.7
C6: Furniture | D6: 1140966.9
C7: Grand Total | D7: 3465455.1
C9: Highest profit category
C11: Row Labels | D11: Sum of Profit
C12: Furniture | D12: 121478.71
C13: Office Supplies | D13: 119851.33
C14: Technology | D14: 118082.57
C15: Grand Total | D15: 359412.61

Sheet Segment Analysis
B2: Best customer segment
B4: Row Labels | C4: Sum of Sales
B5: Consumer | C5: 917791.5
B6: Home Office | C6: 893221.53
B7: Corporate | C7: 841316.09
B8: Small Business | C8: 813125.94
B9: Grand Total | C9: 3465455.1

Sheet SALES PERFORMANCE DASHBOARD
U12: s
P40: SS
